[{"title":"dd","text":"dd","id":"6f71"},{"title":"dsdsd","text":"sdds","id":"62d5"},{"title":"Hello ","text":"Make your tea!","id":"3052"},{"title":"fejvnaekv","text":"zvmaskv","id":"dd37"},{"title":"dsmfv","text":"sf vs","id":"e19e"},{"title":"jj","text":"jjjjj","id":"771a"},{"title":"jj","text":"jjjjj","id":"4c3b"},{"title":"jj","text":"jjjjj","id":"14ac"},{"title":"jj","text":"jjjjj","id":"f262"},{"title":"jj","text":"jjjjj","id":"d0ed"},{"title":"jj","text":"jjjjj","id":"61cf"},{"title":"kk","text":"k","id":"6f46"},{"title":"kk","text":"k","id":"8a0a"},{"title":"nmmm","text":"nnn","id":"7b05"},{"title":"hgg","text":"gjhg","id":"c5cb"},{"title":"hgg","text":"gjhg","id":"8bce"},{"title":"hgg","text":"gjhg","id":"5289"},{"title":"hgg","text":"gjhg","id":"bfea"},{"title":"hgg","text":"gjhg","id":"2f4e"},{"title":"hgg","text":"gjhg","id":"0e62"},{"title":"hgg","text":"gjhg","id":"0fdf"},{"title":"hgg","text":"gjhg","id":"95b0"},{"title":"ok","text":"it works","id":"3170"}]